bocoel/__init__.py
bocoel/__main__.py
bocoel/common/__init__.py
bocoel/common/enums.py
bocoel/common/names.py
bocoel/common/versions.py
bocoel/constants.py
bocoel/core/__init__.py
bocoel/core/exams/__init__.py
bocoel/core/exams/columns/__init__.py
bocoel/core/exams/columns/components.py
bocoel/core/exams/columns/exams.py
bocoel/core/exams/examinators.py
bocoel/core/exams/interfaces.py
bocoel/core/exams/managers.py
bocoel/core/exams/stats/__init__.py
bocoel/core/exams/stats/acc.py
bocoel/core/optim/__init__.py
bocoel/core/optim/ax/__init__.py
bocoel/core/optim/ax/acquisition/__init__.py
bocoel/core/optim/ax/acquisition/entropy.py
bocoel/core/optim/ax/acquisition/supported.py
bocoel/core/optim/ax/optim.py
bocoel/core/optim/ax/params.py
bocoel/core/optim/ax/surrogates/__init__.py
bocoel/core/optim/ax/surrogates/supported.py
bocoel/core/optim/ax/utils.py
bocoel/core/optim/brute.py
bocoel/core/optim/cma/__init__.py
bocoel/core/optim/cma/optim.py
bocoel/core/optim/corpora.py
bocoel/core/optim/interfaces/__init__.py
bocoel/core/optim/interfaces/evals.py
bocoel/core/optim/interfaces/optim.py
bocoel/core/optim/interfaces/utils.py
bocoel/core/optim/random.py
bocoel/core/optim/sklearn/__init__.py
bocoel/core/optim/sklearn/kmeans.py
bocoel/core/optim/sklearn/kmedoids.py
bocoel/core/optim/sklearn/optim.py
bocoel/core/optim/uniform.py
bocoel/core/tasks.py
bocoel/corpora/__init__.py
bocoel/corpora/corpora.py
bocoel/corpora/embedders/__init__.py
bocoel/corpora/embedders/ensemble.py
bocoel/corpora/embedders/huggingface.py
bocoel/corpora/embedders/interfaces.py
bocoel/corpora/embedders/sberts.py
bocoel/corpora/indices/__init__.py
bocoel/corpora/indices/backend/__init__.py
bocoel/corpora/indices/backend/faiss.py
bocoel/corpora/indices/backend/hnswlib.py
bocoel/corpora/indices/interfaces/__init__.py
bocoel/corpora/indices/interfaces/boundaries.py
bocoel/corpora/indices/interfaces/distances.py
bocoel/corpora/indices/interfaces/indices.py
bocoel/corpora/indices/interfaces/results.py
bocoel-0.1.4.dist-info/LICENSE.md
bocoel-0.1.4.dist-info/METADATA
bocoel-0.1.4.dist-info/WHEEL
bocoel-0.1.4.dist-info/RECORD
