Metadata-Version: 2.1
Name: bocoel
Version: 0.1.4
Summary: Bayesian Optimization as a Coverage Tool for Evaluating Large Language Models
License: BSD-3
Author: RenChu Wang
Author-email: patrick1031wang@gmail.com
Requires-Python: >=3.10,<4
Classifier: License :: Other/Proprietary License
Classifier: Programming Language :: Python :: 3
Classifier: Programming Language :: Python :: 3.10
Classifier: Programming Language :: Python :: 3.11
Classifier: Programming Language :: Python :: 3.12
Classifier: Programming Language :: Python :: 3.13
Requires-Dist: PyYAML (>=6.0.2,<7.0.0)
Requires-Dist: alive-progress (>=3.2.0,<4.0.0)
Requires-Dist: ax-platform (>=0.4.3,<0.5.0)
Requires-Dist: botorch (>=0.12.0,<0.13.0)
Requires-Dist: fire (>=0.7.0,<0.8.0)
Requires-Dist: gpytorch (>=1.13,<2.0)
Requires-Dist: networkx (>=3.4.2,<4.0.0)
Requires-Dist: numpy (<2)
Requires-Dist: pandas (>=2.2.3,<3.0.0)
Requires-Dist: parse (>=1.20.2,<2.0.0)
Requires-Dist: scipy (>=1.14.1,<2.0.0)
Requires-Dist: structlog (>=24.4.0,<25.0.0)
Requires-Dist: torch (>=2.5.1,<3.0.0)
Requires-Dist: typeguard (>=4.4.1,<5.0.0)
Requires-Dist: typing-extensions (>=4.12.2,<5.0.0)
